django_enumfield/__init__.py
django_enumfield/app_settings.py
django_enumfield/context_processors.py
django_enumfield/enum.py
django_enumfield/fields.py
django_enumfield/item.py
django_enumfield/utils.py
tests/__init__.py
tests/enums.py
tests/manage.py
tests/models.py
tests/test_settings.py
tests/tests.py
tests/tests_migrations.py
tests/urls.py
tests/app/__init__.py
django_enumfield_ng-1.8.0.dist-info/COPYING
django_enumfield_ng-1.8.0.dist-info/METADATA
django_enumfield_ng-1.8.0.dist-info/WHEEL
django_enumfield_ng-1.8.0.dist-info/top_level.txt
django_enumfield_ng-1.8.0.dist-info/RECORD
