Metadata-Version: 2.1
Name: django-enumfield-ng
Version: 1.8.0
Summary: Type-safe, efficient & database-agnostic enumeration field for Django.
Home-page: https://chris-lamb.co.uk/projects/django-enumfield
Author: Chris Lamb
Author-email: chris@chris-lamb.co.uk
License: BSD
Platform: UNKNOWN
Requires-Python: >=3.6
License-File: COPYING
Requires-Dist: Django (>=2)
